{
  "FirtsName": "Annel",
  "lastNane": "Ricaño ",
  "adress": "street 31, Av. 1 y 2",
  "BirthDate": "03/26/2009",
  "hobbies": [
    "1":"Train gymnasia",
    "2":"listen to music",
    "3":"To walk" 
  ],
  "Friends":[
      "FirstName": "ximena",
  "LastName": "Perez",
  "adress": "Avenue 39b 3341 counts zopilote",
  "BirthDate": "01/08/2009",
  "hobbies": [
    "1":"To dance",
    "2":"Listen to music",
    "3":"To walk" 
  ],
        "FirstName": "Alejandra",
  "LastName": "Porras",
  "adress": "counts vista hermosa, calle nardo",
  "BirthDate": "11/04/2009",
  "hobbies":
    "1":"To read",
    "2":"To dance",
    "3":"Listen to music" 
    ],
      "FirstName": "Tammy",
  "LastName": "Barragan ",
  "adress": "counts la patrona street 4 av.2",
  "BirthDate": "08/19/2009",
  "hobbies": [
    "1":"To read",
    "2":"Listen to music",
    "3":"watch tv" 
  ]
     }
      
      
      
  
  
